neo_cgi
