Metadata-Version: 1.0
Name: clearsilver
Version: 0.10.1
Summary: High performance HTML Template System
Home-page: http://www.clearsilver.net/
Author: Brandon Long
Author-email: blong@fiction.net
License: Apache
Download-URL: http://www.willowmail.com/clearsilver/clearsilver-0.10.1.tar.gz
Keywords: html templates
Platform: UNKNOWN
Classifier: Development Status :: 5 - Production/Stable
Classifier: Environment :: Web Environment
Classifier: Intended Audience :: Developers
Classifier: License :: OSI Approved :: Apache Software License
Classifier: Operating System :: Microsoft :: Windows :: Windows NT/2000
Classifier: Operating System :: POSIX :: BSD
Classifier: Operating System :: POSIX :: Linux
Classifier: Programming Language :: C
Classifier: Topic :: Internet :: WWW/HTTP :: Dynamic Content :: CGI Tools/Libraries
Classifier: Topic :: Software Development :: Localization
Classifier: Topic :: Text Processing :: Markup :: HTML
